wagtail_celery_results/__init__.py
wagtail_celery_results/apps.py
wagtail_celery_results/wagtail_hooks.py
wagtail_celery_results/locale/django.pot
wagtail_celery_results/locale/en/LC_MESSAGES/django.po
wagtail_celery_results/locale/fr/LC_MESSAGES/django.po
wagtail_celery_results-0.1.0.dist-info/licenses/LICENCE
wagtail_celery_results-0.1.0.dist-info/METADATA
wagtail_celery_results-0.1.0.dist-info/WHEEL
wagtail_celery_results-0.1.0.dist-info/top_level.txt
wagtail_celery_results-0.1.0.dist-info/RECORD
